traffic_scene_renderer/__init__.py
traffic_scene_renderer/ambulance.py
traffic_scene_renderer/arrow.py
traffic_scene_renderer/bus.py
traffic_scene_renderer/car.py
traffic_scene_renderer/connection.py
traffic_scene_renderer/crossing.py
traffic_scene_renderer/letters.py
traffic_scene_renderer/options.py
traffic_scene_renderer/path_follower.py
traffic_scene_renderer/polygon.py
traffic_scene_renderer/road_network.py
traffic_scene_renderer/static_objects.py
traffic_scene_renderer/traffic_light.py
traffic_scene_renderer/truck.py
traffic_scene_renderer/utilities.py
traffic_scene_renderer/vehicle.py
traffic_scene_renderer/vertex.py
traffic_scene_renderer/way.py
traffic_scene_renderer-1.1.dist-info/licenses/LICENSE.txt
traffic_scene_renderer-1.1.dist-info/METADATA
traffic_scene_renderer-1.1.dist-info/WHEEL
traffic_scene_renderer-1.1.dist-info/top_level.txt
traffic_scene_renderer-1.1.dist-info/RECORD
